setup.cfg
setup.py
patchboard/__init__.py
patchboard/action.py
patchboard/api.py
patchboard/base.py
patchboard/client.py
patchboard/endpoints.py
patchboard/exception.py
patchboard/headers.py
patchboard/mapping.py
patchboard/resource.py
patchboard/response.py
patchboard/schema_manager.py
patchboard/util.py
patchboard.egg-info/PKG-INFO
patchboard.egg-info/SOURCES.txt
patchboard.egg-info/dependency_links.txt
patchboard.egg-info/not-zip-safe
patchboard.egg-info/pbr.json
patchboard.egg-info/requires.txt
patchboard.egg-info/top_level.txt