Metadata-Version: 1.0
Name: patchboard
Version: 0.5.1
Summary: Python client for Patchboard APIs
Home-page: http://github.com/patchboard/patchboard-py
Author: Matt Smith
Author-email: matt@gem.co
License: MIT
Platform: UNKNOWN
